Workbook

Sheet 概览
A1: SpaceX 财务分析模型 — 2026年5月
A2: 数据来源：SpaceX S-1 IPO招股书（2026年5月）、公司财报、行业报告
A4: 工作表目录
A5: 概览 | B5: 本页 — 模型导航与说明
A6: 分业务财务 | B6: SpaceX三大业务板块（星链/发射/xAI）收入与利润
A7: 星链用户与ARPU | B7: 星链用户增长、营收、EBITDA及ARPU趋势（2023-2026E）
A8: 发射频次与成本 | B8: 猎鹰系列发射频次、回收记录、成本下降曲线
A9: 竞争对比 | B9: SpaceX vs 蓝色起源 vs 火箭实验室 vs ULA vs 波音
A10: 政府合同储备 | B10: NSSL、NASA、SDA、商业发射合同对比
A11: 估值情景 | B11: 牛市/基础/熊市/Damodaran DCF 估值情景
A12: IPO详情 | B12: IPO关键参数、估值背景、募集资金用途
A13: TAM市场 | B13: 可寻址市场总量：发射/宽带/国防/轨道AI
A14: 数据校验 | B14: 跨表数据一致性校验
A17: 配色约定
A18: 蓝色字体 | B18: =手动输入的硬编码数据
A19: 黑色字体 | B19: =公式计算
A20: 绿色字体 | B20: =跨表链接

Sheet 分业务财务
A1: SpaceX 分业务财务数据（FY2024–FY2025）
A2: 单位：亿美元（除特别标注）。FY2024为近似值（公司当时为私有）。xAI于2026年2月并入SpaceX。
A4: 业务板块 | B4: FY2024营收 | C4: FY2025营收 | D4: 同比增速 | E4: 运营利润/(亏损) FY2025 | F4: EBITDA FY2025 | G4: EBITDA利润率 / 备注
A5: 星链（连接业务） | B5: 76 | C5: 113.9 | D5: =(C5-B5)/B5 | E5: 44.2 | F5: 71.7 | G5: 63%
A6: 发射服务 | B6: 38 | C6: 40.9 | D6: =(C6-B6)/B6 | E6: -6.6 | F6: - | G6: 含星舰R&D $30亿/年
A7: xAI（人工智能） | B7: - | C7: 32 | D7: 不可比 | E7: -63.6 | F7: - | G7: 资本支出$127亿
A8: 合并总计 | B8: 114 | C8: 186.7 | D8: =(C8-B8)/B8 | E8: -25.9 | F8: 15 | G8: 净亏损($49.4亿)
A10: 注：星链EBITDA利润率63%为2025全年数据。合并调整后EBITDA约$15亿为近似值。

Sheet 星链用户与ARPU
A1: 星链 — 用户增长与单位经济（2023–2026E）
A2: 数据来源：SpaceX S-1招股书（2026年5月）；Quilty Space星链财务概览2026；Morningstar。
A4: 指标 | B4: 2023 | C4: 2024 | D4: 2025 | E4: Q1 2026 | F4: 2026E
A5: 用户数（百万） | B5: 2.3 | C5: 4.4 | D5: 8.9 | E5: 10.3 | F5: 1,680–2,500万
A6: 营收（亿美元） | B6: 51 | C6: 76 | D6: 113.9 | E6: 32.6 | F6: 187–200亿
A7: 运营利润（亿美元） | B7: 20 | C7: 20 | D7: 44.2 | E7: 11.9 | F7: —
A8: EBITDA（亿美元） | B8: 25 | C8: 38.6 | D8: 71.7 | E8: — | F8: ~140亿
A9: EBITDA利润率 | B9: =C8/C6 | C9: =D8/D6 | D9: =E8/E6 | E9: — | F9: ~70%
A10: 月均ARPU（美元） | B10: 99 | C10: 91 | D10: 81 | E10: 66 | F10: 策略性下降

Sheet 发射频次与成本
A1: 猎鹰系列 — 发射频次与成本下降曲线（2020–2025）
A2: 数据来源：SpaceX S-1；NextBigFuture；IndexBox；维基百科。内部成本为估算值。
A4: 年份 | B4: Falcon发射次数 | C4: 累计着陆次数 | D4: 成本/kg至LEO 内部($) | E4: 成本/kg至LEO 客户($) | F4: 复用次数(max) | G4: 发射市场份额
A5: 2020 | B5: 26 | C5: 70 | D5: 1200 | E5: 4400 | F5: 5 | G5: ~50%
A6: 2021 | B6: 31 | C6: 100 | D6: 1000 | E6: 3800 | F6: 8 | G6: ~45%
A7: 2022 | B7: 61 | C7: 150 | D7: 850 | E7: 3200 | F7: 12 | G7: ~55%
A8: 2023 | B8: 96 | C8: 220 | D8: 750 | E8: 2900 | F8: 17 | G8: ~65%
A9: 2024 | B9: 134 | C9: 350 | D9: 700 | E9: 2750 | F9: 25 | G9: ~75%
A10: 2025 | B10: 165 | C10: 571 | D10: 629 | E10: 2720 | F10: 33 | G10: >80%
A11: 合计/平均 | B11: =SUM(B5:B10)
A13: 成本下降CAGR (2020-2025) | D13: 内部成本CAGR: | E13: =(D10/D5)^(1/5)-1

Sheet 竞争对比
A1: 航天发射领域竞争对比（2025年数据）
A2: 数据来源：公司财报；SEC EDGAR；SpaceX S-1；火箭实验室Q1 2026财报；行业估算。波音航天为BDS中估算占比<15%。
A4: 指标 | B4: SpaceX | C4: 蓝色起源 | D4: 火箭实验室(RKLB) | E4: ULA | F4: 波音(航天)
A5: 营收（航天,亿美元） | B5: $186.7亿 | C5: <$5亿（估） | D5: $6.018亿 | E5: $10–20亿（估） | F5: ~$40亿（估）
A6: 2025发射次数 | B6: 165 | C6: 2 | D6: 21 | E6: 5 | F6: —
A7: 助推器最大复用次数 | B7: 33 | C7: 1（2025.11） | D7: 0（部分回收） | E7: 0（一次性） | F7: 0
A8: 单次发射价格（$百万） | B8: $70 | C8: $60–70 | D8: $8.5（电子号） | E8: $100–200 | F8: —
A9: 垂直整合度 | B9: 85–90% | C9: 中等 | D9: 中等（并购扩张） | E9: 低（仅组装） | F9: 中等
A10: 消费宽带 | B10: 星链1,030万用户 | C10: 无 | D10: 无 | E10: 无 | F10: 无
A11: 累计着陆次数 | B11: 571 | C11: 1 | D11: 部分溅落回收 | E11: 0 | F11: 0
A12: 下一代火箭 | B12: 星舰（试飞中） | C12: 新格伦（运营） | D12: 中子（2026Q4） | E12: 无计划 | F12: SLS（成本加成）

Sheet 政府合同储备
A1: 政府及商业发射合同储备对比
A2: 数据来源：美国太空军NSSL Phase 3合同（2025年4月/9月）；NASA HLS；SDA；ULA/蓝色起源新闻稿。
A4: 合同项目 | B4: SpaceX | C4: 蓝色起源 | D4: 火箭实验室 | E4: ULA
A5: NSSL Phase 3（太空军） | B5: 28次任务 / $59亿 | C5: 7次任务 / $23亿 | D5: — | E5: 19次任务 / $53亿
A6: NASA（阿尔忒弥斯/HLS等） | B6: $30亿+（HLS月球着陆器） | C6: $34亿（蓝月着陆器） | D6: — | E6: —
A7: SDA（太空发展局） | B7: 多个合同（卫星平台） | C7: — | D7: $8.16亿（Tranche III） | E7: —
A8: 商业发射（Kuiper等） | B8: —（星链自用165次） | C8: Kuiper部分发射 | D8: 70+次电子号订单 | E8: 47次Kuiper发射
A9: 载人航天 | B9: 商业载人（NASA $50亿+） | C9: — | D9: — | E9: —
A10: 注：合同金额为总合同额，非年化。实际入账按交付进度确认。

Sheet 估值情景
A1: SpaceX 估值情景分析（2028E）
A2: 说明：所有情景均为说明性分析，基于S-1文件及行业研究中公开可获取的信息。
A4: 情景 | B4: 概率 | C4: 星链用户2028E（百万） | D4: 星链EBITDA 2028E（亿美元） | E4: 隐含估值（万亿美元） | F4: 隐含EV/EBITDA | G4: 关键假设
A5: ▲ 牛市 | B5: 0.3 | C5: 40 | D5: 300 | E5: 2.75 | F5: =E5/D5*1000 | G5: 星舰完全复用成功；40M+用户；轨道AI变现
A6: ► 基础 | B6: 0.5 | C6: 25 | D6: 180 | E6: 1.75 | F6: =E6/D6*1000 | G6: 星舰部分复用；Kuiper入市竞争；xAI亏损收窄
A7: ▼ 熊市 | B7: 0.2 | C7: 15 | D7: 100 | E7: 0.65 | F7: =E7/D7*1000 | G7: 星舰推迟；ARPU持续下降；Anthropic取消合同
A8: Damodaran DCF | B8: — | C8: 20 | D8: 150 | E8: 1.22 | F8: =E8/D8*1000 | G8: 学术估值基准；较IPO目标低~30%
A9: IPO目标（中点） | B9: — | C9: 25 | D9: 180 | E9: 1.75 | F9: =E9/D9*1000 | G9: S-1披露估值区间中点
A11: 概率加权预期估值 | E11: =SUMPRODUCT(B5:B7,E5:E7)
A13: 情景概率分布
A14: 情景 | B14: 概率
A15: 牛市 | B15: 0.3
A16: 基础 | B16: 0.5
A17: 熊市 | B17: 0.2

Sheet IPO详情
A1: SpaceX IPO — 关键参数与估值背景
A2: 数据来源：SpaceX S-1 IPO招股书（2026年5月）；Reuters；PitchBook；Morningstar。
A4: 参数 | B4: 数值 | C4: 备注/对比
A5: 预计上市日期 | B5: 2026年6月12日 | C5: 窗口可能因市场条件调整
A6: 交易所 / 代码 | B6: NASDAQ: SPCX | C6: 双类股权结构
A7: 目标估值 | B7: $1.75–2.0万亿美元 | C7: 史上最大IPO（沙特阿美$256亿为当前记录）
A8: 目标融资规模 | B8: ~$750亿 | C8: 含一级发行+二级出售
A9: 2025年营收对应P/S | B9: ~94–107× | C9: SaaS行业中位数约8–10×
A10: 马斯克投票权（IPO后） | B10: 85.1% | C10: B类股 10票/股 vs A类股 1票/股
A11: 2025年营收 | B11: $186.7亿 | C11: 星链61% + 发射22% + xAI 17%
A12: 2025年净亏损 | B12: ($49.4亿) | C12: 含xAI $63.6亿运营亏损
A13: 2025年资本支出 | B13: $207.4亿 | C13: 含xAI $127亿基础设施投资
A14: 累计亏损（成立至今） | B14: $413.1亿 | C14: 主要来自星舰研发和xAI投资
A15: 员工数（估） | B15: ~15,000+ | C15: 含xAI团队
A16: IPO主承销商 | B16: 待披露 | C16: 预计多家顶级投行联席承销
A19: 募集资金用途（据S-1招股书）
A20: • 星舰基础设施与制造规模化——Boca Chica、卡纳维拉尔角及额外发射场
A21: • 星链V3卫星生产与星座扩展——目标30,000+颗卫星
A22: • xAI / Colossus超级计算机扩展——GPU集群、数据中心、轨道计算研发
A23: • 一般企业用途——营运资金、潜在收购、债务偿还
A24: • 现有股东流动性——预计部分为二次发行

Sheet TAM市场
A1: 可寻址市场总量（TAM）— 航天经济各板块
A2: 数据来源：SpaceX S-1；Quilty Space；McKinsey；Morgan Stanley航天产业估算；SDA。
A4: 市场板块 | B4: 当前规模（亿美元） | C4: 增速（CAGR） | D4: 2030E规模（亿美元） | E4: SpaceX定位 | F4: 竞争优势
A5: 发射服务 | B5: 200 | C5: 0.09 | D5: =B5*(1+C5)^4 | E5: 主导（>80%份额） | F5: 可重复使用、成本、发射频次
A6: 卫星宽带 | B6: 400 | C6: 0.22 | D6: =B6*(1+C6)^4 | E6: 先发领导者（星链） | F6: 用户规模、在轨卫星数、品牌
A7: 政府/国防航天 | B7: 500 | C7: 0.12 | D7: =B7*(1+C7)^4 | E7: 低成本在位者 | F7: NSSL合同、安全许可、可靠性
A8: 轨道AI与数据服务 | B8: 500 | C8: 0.35 | D8: =B8*(1+C8)^4 | E8: xAI押注（新兴） | F8: 星舰运力、垂直整合、资本
A9: 合计/交叉 | B9: =SUM(B5:B8) | E9: 多板块整合运营商 | F9: 全栈控制 = 利润获取

Sheet 数据校验
A1: 跨表数据一致性校验
A2: 校验规则：对比各表中相同指标数值，确保一致性。TRUE = 一致，FALSE = 不一致，需排查。
A4: 校验项 | B4: 表1数值 | C4: 表2数值 | D4: 结果
A5: 星链FY2025营收 | B5: ='分业务财务'!C5 | C5: 113.9 | D5: =ROUND(B5,1)=ROUND(C5,1)
A6: 发射FY2025营收 | B6: ='分业务财务'!C6 | C6: 40.9 | D6: =ROUND(B6,1)=ROUND(C6,1)
A7: 合并FY2025营收 | B7: ='分业务财务'!C8 | C7: 186.7 | D7: =ROUND(B7,1)=ROUND(C7,1)
A8: 星链FY2025 EBITDA | B8: ='分业务财务'!F5 | C8: 71.7 | D8: =ROUND(B8,1)=ROUND(C8,1)
A9: 2025发射次数 | B9: ='发射频次与成本'!B10 | C9: 165 | D9: =ROUND(B9,1)=ROUND(C9,1)
A10: 2025累计着陆 | B10: ='发射频次与成本'!C10 | C10: 571 | D10: =ROUND(B10,1)=ROUND(C10,1)
A11: 星链2025用户数 | B11: ='星链用户与ARPU'!D5 | C11: 8.9 | D11: =ROUND(B11,1)=ROUND(C11,1)
A12: IPO目标估值(中点) | B12: ='估值情景'!E9 | C12: 1.75 | D12: =ROUND(B12,1)=ROUND(C12,1)
A14: 所有数据源自SpaceX S-1招股书（2026年5月）及公开行业报告。数字经人工核对，保留1位小数精度。
